.gitignore
CHANGES.txt
LICENSE.txt
MANIFEST.in
README.rst
setup.py
boto3_paste/__init__.py
boto3_paste.egg-info/PKG-INFO
boto3_paste.egg-info/SOURCES.txt
boto3_paste.egg-info/dependency_links.txt
boto3_paste.egg-info/not-zip-safe
boto3_paste.egg-info/requires.txt
boto3_paste.egg-info/top_level.txt
boto3_paste/tests/__init__.py
boto3_paste/tests/config_1.ini
boto3_paste/tests/cred_1.ini
boto3_paste/tests/test_boto3_paste.py