Metadata-Version: 1.1
Name: boto3-paste
Version: 0.1
Summary: Adapt boto3 to paste
Home-page: https://github.com/gjo/boto3_paste
Author: OCHIAI, Gouji
Author-email: gjo.ext@gmail.com
License: BSD
Platform: UNKNOWN
Classifier: Framework :: Paste
Classifier: Framework :: Pyramid
Classifier: License :: OSI Approved :: BSD License
Classifier: Programming Language :: Python
Classifier: Programming Language :: Python :: 2.7
Classifier: Programming Language :: Python :: 3.5
